scli/__init__.py
scli/contributors/__init__.py
scli/contributors/dds.py
scli-0.0.5.dist-info/LICENSE
scli-0.0.5.dist-info/METADATA
scli-0.0.5.dist-info/WHEEL
scli-0.0.5.dist-info/top_level.txt
scli-0.0.5.dist-info/RECORD
