Metadata-Version: 2.1
Name: scli
Version: 0.0.5
Summary: Package to make a world better place
Home-page: https://github.com/pypa/sampleproject
Author: Anonymous Boy
Author-email: sourav.pes@gmail.com
License: UNKNOWN
Project-URL: Bug Tracker, https://github.com/pypa/sampleproject/issues
Platform: UNKNOWN
Classifier: Programming Language :: Python :: 3
Classifier: License :: OSI Approved :: MIT License
Classifier: Operating System :: OS Independent
Requires-Python: >=3.6
